hyron/__init__.py
hyron/constants.py
hyron/helpers.py
hyron/objects_stanza_handler.py
hyron/apps/__init__.py
hyron/apps/application.py
hyron/apps/application_group.py
hyron/apps/application_library.py
hyron/apps/application_library_loader.py
hyron/artifacts/__init__.py
hyron/artifacts/artifact.py
hyron/artifacts/artifact_blueprint.py
hyron/artifacts/artifact_file.py
hyron/artifacts/artifact_file_blueprint.py
hyron/assets/cli_header.txt
hyron/assets/cli_usage.txt
hyron/builtin/apps.yaml
hyron/builtin/prefixlists.yaml
hyron/prefixlists/__init__.py
hyron/prefixlists/prefix_list.py
hyron/prefixlists/prefix_list_datasource.py
hyron/prefixlists/prefix_list_loader.py
hyron/prefixlists/datasources/__init__.py
hyron/prefixlists/datasources/aws.py
hyron/prefixlists/datasources/jsonquery.py
hyron/prefixlists/datasources/merge.py
hyron/prefixlists/datasources/static.py
hyron/prefixlists/datasources/web.py
hyron/renderers/__init__.py
hyron/renderers/renderer.py
hyron/renderers/aws/__init__.py
hyron/renderers/aws/aws_ec2_security_group_renderer.py
hyron/renderers/junos/__init__.py
hyron/renderers/junos/junos_command_builder.py
hyron/renderers/junos/srx/__init__.py
hyron/renderers/junos/srx/junos_srx_renderer.py
hyron/renderers/junos/srx/datastructures/__init__.py
hyron/renderers/junos/srx/datastructures/junos_srx_address.py
hyron/renderers/junos/srx/datastructures/junos_srx_address_set.py
hyron/renderers/junos/srx/datastructures/junos_srx_application.py
hyron/renderers/junos/srx/datastructures/junos_srx_datastructure.py
hyron/renderers/junos/srx/datastructures/junos_srx_rule.py
hyron/renderers/junos/srx/formats/__init__.py
hyron/renderers/junos/srx/formats/junos_srx_command_renderer.py
hyron/renderers/junos/srx/formats/junos_srx_json_renderer.py
hyron/renderers/junos/srx/zone_providers/__init__.py
hyron/renderers/junos/srx/zone_providers/zone_provider.py
hyron/rulebooks/__init__.py
hyron/rulebooks/rule_builder.py
hyron/rulebooks/rulebook.py
hyron/rulebooks/rulebook_loader.py
hyron-0.2.1.dist-info/LICENSE
hyron-0.2.1.dist-info/METADATA
hyron-0.2.1.dist-info/WHEEL
hyron-0.2.1.dist-info/top_level.txt
hyron-0.2.1.dist-info/RECORD
